{"cameraMode":{"drawMode":0,"name":"Shaded","section":"Shading Mode"},"sceneLighting":true,"audioPlay":false,"sceneViewState":{"m_AlwaysRefresh":false,"showFog":true,"showSkybox":true,"showFlares":true,"showImageEffects":true,"showParticleSystems":true,"showVisualEffectGraphs":true,"m_FxEnabled":true},"in2DMode":false,"pivot":{"x":45.96841049194336,"y":-28.057262420654298,"z":1.9947081804275513},"rotation":{"x":-0.19006328284740449,"y":-0.673390805721283,"z":0.18554554879665376,"w":-0.6900783181190491},"size":31.09368896484375,"orthographic":false}